Workbook

Sheet A. General Information
A1: A. General Information
A3: A0 | B3: Respondent Information
B4: Name: | D4: Cecila King
B5: Title: | D5: Data Management Coordinator
B6: Office: | D6: Office of Institutional Research and Effectiveness
B7: Mailing Address: | D7: P.O. Drawer EY
B8: City/State/Zip/Country: | D8: Mississippi State, MS 39762 U.S.A.
B9: Phone: | D9: 662-325-3920
B10: Fax: | D10: 662-325-3514
B11: E-mail Address: | D11: oir@ir.msstate.edu
B12: Are your responses to the CDS posted for reference on your institution's Web site? | E12: Yes | F12: No
E13: X
B14: If yes, please provide the URL of the corresponding Web page:
B15: http://www.ir.msstate.edu/
B17: We invite you to indicate if there are items on the CDS for which you cannot use the requested analytic convention, cannot provide data for the cohort requested, whose methodology is unclear, or about which you have questions or comments in general. This information will not be published but will help the publishers further refine CDS items.
A20: A1 | B20: Address Information
B21: Name of College/University: | C21: Mississippi State University
B22: Mailing Address: | C22: P.O. Box 6018
B23: City/State/Zip/Country: | C23: Mississippi State, MS 39762 U.S.A.
B24: Street Address (if different):
B25: City/State/Zip/Country:
B26: Main Phone Number: | C26: 662-325-2323
B27: WWW Home Page Address: | C27: www.msstate.edu
B28: Admissions Phone Number: | C28: 662-325-2224
B29: Admissions Toll-Free Phone Number:
B30: Admissions Office Mailing Address: | C30: P.O. Box 6334
B31: City/State/Zip/Country: | C31: Mississippi State, MS 39762 U.S.A.
B32: Admissions Fax Number: | C32: (662) 325-1MSU
B33: Admissions E-mail Address: | C33: admit@msstate.edu
B34: If there is a separate URL for your school’s online application, please specify: | C34: http://www.msstate.edu/future-students/apply/
B35: If you have a mailing address other than the above to which applications should be sent, please provide:
A37: A2 | B37: Source of institutional control (Check only one):
B38: Public | C38: X
B39: Private (nonprofit)
B40: Proprietary
A42: A3 | B42: Classify your undergraduate institution:
B43: Coeducational college | C43: X
B44: Men's college
B45: Women's college
A47: A4 | B47: Academic year calendar:
B49: Semester | C49: X
B50: Quarter
B51: Trimester
B52: 4-1-4
B53: Continuous
B54: Differs by program (describe):
B56: Other (describe):
A60: A5 | B60: Degrees offered by your institution:
B62: Certificate
B63: Diploma
B64: Associate
B65: Transfer Associate
B66: Terminal Associate
B67: Bachelor's degree | C67: X
B68: Postbachelor's certificate | C68: X
B69: Master's degree | C69: X
B70: Post-master's degree | C70: X
B71: Post-master's certificate | C71: X
B72: Doctoral degree - research/scholarship | C72: X
B73: Doctoral degree - professional practice | C73: X
B74: Doctoral degree - other
A75: A5 | B75: Doctoral degree -- other

Sheet B. Enrollment and Persistence
A1: B. ENROLLMENT AND PERSISTENCE
A3: B1 | B3: Institutional Enrollment Men and Women - Provide numbers of students for each of the following categories as of the institution's official fall reporting date.
B4: • Note: Report students formerly designated as “first professional” in the graduate cells.
C6: FULL-TIME | E6: PART-TIME
C7: Men | D7: Women | E7: Men | F7: Women
B8: Undergraduates | H8: men | I8: women | J8: total | L8: ft | M8: pt
B9: Degree-seeking, first-time freshmen | C9: 1612 | D9: 1741 | E9: 6 | F9: 8 | G9: ugrad | H9: =SUM(C9+E9) -> 1618 | I9: =SUM(D9+F9) -> 1749 | J9: =SUM(H9:I9) -> 3367 | L9: =SUM(C9:D9) -> 3353 | M9: =SUM(E9:F9) -> 14
B10: Other first-year, degree-seeking | C10: 822 | D10: 827 | E10: 76 | F10: 104 | H10: =SUM(C10+E10) -> 898 | I10: =SUM(D10+F10) -> 931 | J10: =SUM(H10:I10) -> 1829 | L10: =SUM(C10:D10) -> 1649 | M10: =SUM(E10:F10) -> 180
B11: All other degree-seeking | C11: 5590 | D11: 5785 | E11: 735 | F11: 598 | H11: =SUM(C11+E11) -> 6325 | I11: =SUM(D11+F11) -> 6383 | J11: =SUM(H11:I11) -> 12708 | L11: =SUM(C11:D11) -> 11375 | M11: =SUM(E11:F11) -> 1333
B12: Total degree-seeking | C12: =SUM(C9:C11) -> 8024 | D12: =SUM(D9:D11) -> 8353 | E12: =SUM(E9:E11) -> 817 | F12: =SUM(F9:F11) -> 710 | H12: =SUM(C12+E12) -> 8841 | I12: =SUM(D12+F12) -> 9063 | J12: =SUM(H12:I12) -> 17904 | L12: =SUM(C12:D12) -> 16377 | M12: =SUM(E12:F12) -> 1527
B13: All other undergraduates enrolled in credit courses | C13: 140 | D13: 104 | E13: 85 | F13: 72 | H13: =SUM(C13+E13) -> 225 | I13: =SUM(D13+F13) -> 176 | J13: =SUM(H13:I13) -> 401 | L13: =SUM(C13:D13) -> 244 | M13: =SUM(E13:F13) -> 157
B14: Total undergraduates | C14: =SUM(C12:C13) -> 8164 | D14: =SUM(D12:D13) -> 8457 | E14: =SUM(E12:E13) -> 902 | F14: =SUM(F12:F13) -> 782 | H14: =SUM(C14+E14) -> 9066 | I14: =SUM(D14+F14) -> 9239 | J14: =SUM(H14:I14) -> 18305 | L14: =SUM(C14:D14) -> 16621 | M14: =SUM(E14:F14) -> 1684
B15: Graduate | G15: grad
B16: Degree-seeking, first-time | C16: 182 | D16: 255 | E16: 103 | F16: 114 | H16: =SUM(C16+E16) -> 285 | I16: =SUM(D16+F16) -> 369 | J16: =SUM(H16:I16) -> 654 | L16: =SUM(C16:D16) -> 437 | M16: =SUM(E16:F16) -> 217
B17: All other degree-seeking | C17: 697 | D17: 1003 | E17: 901 | F17: 1014 | H17: =SUM(C17+E17) -> 1598 | I17: =SUM(D17+F17) -> 2017 | J17: =SUM(H17:I17) -> 3615 | L17: =SUM(C17:D17) -> 1700 | M17: =SUM(E17:F17) -> 1915
B18: All other graduates enrolled in credit courses | C18: 1 | D18: 3 | E18: 35 | F18: 36 | H18: =SUM(C18+E18) -> 36 | I18: =SUM(D18+F18) -> 39 | J18: =SUM(H18:I18) -> 75 | L18: =SUM(C18:D18) -> 4 | M18: =SUM(E18:F18) -> 71
B19: Total graduate | C19: =SUM(C16:C18) -> 880 | D19: =SUM(D16:D18) -> 1261 | E19: =SUM(E16:E18) -> 1039 | F19: =SUM(F16:F18) -> 1164 | H19: =SUM(C19+E19) -> 1919 | I19: =SUM(D19+F19) -> 2425 | J19: =SUM(H19:I19) -> 4344 | L19: =SUM(C19:D19) -> 2141 | M19: =SUM(E19:F19) -> 2203
C20: =SUM(C19+C14) -> 9044 | D20: =SUM(D19+D14) -> 9718 | E20: =SUM(E19+E14) -> 1941 | F20: =SUM(F19+F14) -> 1946
B21: Total all undergraduates | C21: =SUM(C14+C19) -> 9044 | D21: =SUM(D14+D19) -> 9718 | E21: =SUM(E14+E19) -> 1941 | F21: =SUM(C14:F14) -> 18305 | H21: =SUM(C14+C19) -> 9044 | I21: =SUM(D14+D19) -> 9718 | J21: =SUM(E14+E19) -> 1941 | K21: =SUM(F14+F19) -> 1946 | L21: =SUM(H21:K21) -> 22649
B22: Total all graduate | F22: =SUM(C19:F19) -> 4344
B23: GRAND TOTAL ALL STUDENTS | F23: =SUM(F21:F22) -> 22649
A25: B2 | B25: Enrollment by Racial/Ethnic Category - Provide numbers of undergraduate students for each of the following categories as of the institution's official fall reporting date.
B26: • Include international students only in the category "Nonresident aliens."
B27: • Complete the “Total Undergraduates” column only if you cannot provide data for the first two columns.
B28: • Report as your institution reports to IPEDS: persons who are Hispanic should be reported only on the Hispanic line, not under any race, and persons who are non-Hispanic multi-racial should be reported only under "Two or more races."
D29: Degree-Seeking First-Time First Year | E29: Degree-Seeking Undergraduates (include first-time first-year) | F29: Total Undergraduates (both degree- and non-degree-seeking)
B30: Nonresident aliens | D30: 36 | E30: 206 | F30: 215
B31: Hispanic/Latino | D31: 130 | E31: 687 | F31: 701
B32: Black or African American, non-Hispanic | D32: 545 | E32: 2721 | F32: 2812
B33: White, non-Hispanic | D33: 2448 | E33: 13322 | F33: 13582
B34: American Indian or Alaska Native, non-Hispanic | D34: 14 | E34: 95 | F34: 96
B35: Asian, non-Hispanic | D35: 59 | E35: 283 | F35: 294
B36: Native Hawaiian or other Pacific Islander, non-Hispanic | D36: 1 | E36: 7 | F36: 9
B37: Two or more races, non-Hispanic | D37: 107 | E37: 460 | F37: 469
B38: Race and/or ethnicity unknown | D38: 27 | E38: 123 | F38: 127
B39: TOTAL | D39: =SUM(D30:D38) -> 3367 | E39: =SUM(E30:E38) -> 17904 | F39: =SUM(F30:F38) -> 18305
B41: Persistence
A42: B3 | B42: Number of degrees awarded from July 1, 2021 to June 30, 2022
B43: Certificate/diploma
B44: Associate degrees
B45: Bachelor's degrees | C45: 4213
B46: Postbachelor's certificates
B47: Master's degrees | C47: 1083
B48: Post-Master's certificates
B49: Post-Master's degrees | C49: 46
B50: Doctoral degrees – research/scholarship | C50: 173
B51: Doctoral degrees – professional practice | C51: 94
B52: Doctoral degrees – other | E52: =SUM(C45:C51) -> 5609
C53: =SUM(C45:C51) -> 5609
B55: Graduation Rates
B56: The items in this section correspond to data elements collected by the IPEDS Web-based Data Collection System’s Graduation Rate Survey (GRS). For complete instructions and definitions of data elements, see the IPEDS GRS Forms and Instructions for the 2021-21 Survey
B58: For Bachelor's or Equivalent Institutions
B59: In the following section for bachelor’s or equivalent programs, please disaggregate the Fall 2016 cohorts into four groups:
B60: • Students who received a Federal Pell Grant*
B61: • Recipients of a subsidized Stafford Loan who did not receive a Pell Grant
B62: • Students who did not receive either a Pell Grant or a subsidized Stafford Loan
B63: • Total (all students, regardless of Pell Grant or subsidized loan status)
B64: * Students who received both a Federal Pell Grant and a subsidized Stafford Loan should be reported in the "Recipients of a Federal Pell Grant" column.
B65: For each graduation rate grid below, the numbers in the first three columns for Questions A-G should sum to the cohort total in the fourth column.
B67: Fall 2016 Cohort
C68: Recipients of a Federal Pell Grant | D68: Recipients of a Subsidized Stafford Loan who did not receive a Pell Grant | E68: Students who did not receive either a Pell Grant or a subsidized Stafford Loan | F68: Total (sum of 3 columns to the left)
A70: B4 | B70: A -Initial 2016 cohort of first-time, full-time, bachelor's (or equivalent) degree-seeking undergraduate students | C70: 1180 | D70: 535 | E70: 1902 | F70: =SUM(C70:E70) -> 3617
A71: B5 | B71: B - Of the initial 2016 cohort, how many did not persist and did not graduate for the following reasons: • Deceased • Permanently Disabled • Armed Forces • Foreign Aid Service of the Federal Government • Official church missions • Report Total Allowable Exclusions | C71: 1 | D71: 0 | E71: 1 | F71: =SUM(C71:E71) -> 2
A72: B6 | B72: C - Final 2016 cohort, after adjusting for allowable exclusions | C72: =C70-C71 -> 1179 | D72: =D70-D71 -> 535 | E72: =E70-E71 -> 1901 | F72: =SUM(C72:E72) -> 3615
A73: B7 | B73: D - Of the initial 2016 cohort, how many completed the program in four years or less (by Aug. 31, 2020) | C73: 312 | D73: 217 | E73: 957 | F73: =SUM(C73:E73) -> 1486
A74: B8 | B74: E - Of the initial 2016 cohort, how many completed the program in more than four years but in five years or less (after Aug. 31, 2020 and by Aug. 31, 2021) | C74: 189 | D74: 98 | E74: 385 | F74: =SUM(C74:E74) -> 672
A75: B9 | B75: F - Of the initial 2016 cohort, how many completed the program in more than five years but in six years or less (after Aug. 31, 2021 and by Aug. 31, 2022) | C75: 52 | D75: 15 | E75: 56 | F75: =SUM(C75:E75) -> 123
A76: B10 | B76: G - Total graduating within six years (sum of lines D, E, and F) | C76: =SUM(C73:C75) -> 553 | D76: =SUM(D73:D75) -> 330 | E76: =SUM(E73:E75) -> 1398 | F76: =SUM(C76:E76) -> 2281
A77: B11 | B77: H - Six-year graduation rate for 2016 cohort (G divided by C) | C77: =C76/C72 -> 0.46904156 | D77: =D76/D72 -> 0.61682243 | E77: =E76/E72 -> 0.73540242 | F77: =F76/F72 -> 0.63098202
B79: Fall 2015 Cohort
C80: Recipients of a Federal Pell Grant | D80: Recipients of a Subsidized Stafford Loan who did not receive a Pell Grant | E80: Students who did not receive either a Pell Grant or a subsidized Stafford Loan | F80: Total (sum of 3 columns to the left)
A82: B4 | B82: A- Initital 2015 cohort of first-time, full-time bachelor's (or equivalent) degree seeking undergraduate-students | C82: 1161 | D82: 475 | E82: 1823 | F82: =SUM(C82:E82) -> 3459
A83: B5 | B83: B- Of the initial 2015 cohort, how many did not persist and did not graduate for the following reasons: deceased, permanently disabled, armed forces, foreign aid service of the federal government, or official church missions; total allowable exclusions | C83: 2 | D83: 0 | E83: 3 | F83: =SUM(C83:E83) -> 5
A84: B6 | B84: C- Final 2015 cohort, after adjusting for allowable exclusions | C84: =C82-C83 -> 1159 | D84: =D82-D83 -> 475 | E84: =E82-E83 -> 1820 | F84: =SUM(C84:E84) -> 3454
A85: B7 | B85: D - Of the initial 2015 cohort, how many completed the program in four years or less (by Aug. 31, 2019) | C85: 282 | D85: 169 | E85: 802 | F85: =SUM(C85:E85) -> 1253
A86: B8 | B86: E - Of the initial 2015 cohort, how many completed the program in more than four years but in five years or less (after Aug. 31, 2019 and by Aug. 31, 2020) | C86: 208 | D86: 87 | E86: 383 | F86: =SUM(C86:E86) -> 678
A87: B9 | B87: F - Of the initial 2015 cohort, how many completed the program in more than five years but in six years or less (after Aug. 31, 2020 and by Aug. 31, 2021) | C87: 51 | D87: 13 | E87: 63 | F87: =SUM(C87:E87) -> 127
A88: B10 | B88: G - Total graduating within six years (sum of lines D, E, and F) | C88: 543 | D88: =SUM(D85:D87) -> 269 | E88: 1251 | F88: =SUM(C88:E88) -> 2063
A89: B11 | B89: H - Six-year graduation rate for 2015 cohort (G divided by C) | C89: =C88/C84 -> 0.46850733 | D89: =D88/D84 -> 0.56631579 | E89: =E88/E84 -> 0.68736264 | F89: =F88/F84 -> 0.59727852
B91: Retention Rates
B92: Report for the cohort of all full-time, first-time bachelor’s (or equivalent) degree-seeking undergraduate students who entered in Fall 2021 (or the preceding summer term). The initial cohort may be adjusted for students who departed for the following reasons: death, permanent disability, service in the armed forces, foreign aid service of the federal government or official church missions. No other adjustments to the initial cohort should be made.
A93: B20 | B93: For the cohort of all full-time bachelor’s (or equivalent) degree-seeking undergraduate students who entered your institution as freshmen in Fall 2021 (or the preceding summer term), what percentage was enrolled at your institution as of the date your institution calculates its official enrollment in Fall 2022? | F93: 0.805 | H93: =2716/3372 -> 0.8054567
B96: Fall 2014 Cohort
C97: Recipients of a Federal Pell Grant | D97: Recipients of a Subsidized Stafford Loan who did not receive a Pell Grant | E97: Students who did not receive either a Pell Grant or a subsidized Stafford Loan | F97: Total (sum of 3 columes to the left)
A99: B12 | B99: A- Initital 2014 cohort of first-time, full-time bachelor's (or equivalent) degree seeking undergraduate-students | F99: =SUM(C99:E99) -> 0
A100: B13 | B100: B- Of the initial 2014 cohort, how many did not persist and did not graduate for the following reasons: deceased, permanently disabled, armed forces, foreign aid service of the federal government, or official church missions; total allowable exclusions | F100: =SUM(C100:E100) -> 0
A101: B14 | B101: C- Final 2014 cohort, after adjusting for allowable exclusions | C101: =C99-C100 -> 0 | D101: =D99-D100 -> 0 | E101: =E99-E100 -> 0 | F101: =SUM(C101:E101) -> 0
A102: B15 | B102: D - Of the initial 2014 cohort, how many completed the program in four years or less (by Aug. 31, 2018) | F102: =SUM(C102:E102) -> 0
A103: B16 | B103: E - Of the initial 2014 cohort, how many completed the program in more than four years but in five years or less (after Aug. 31, 2017 and by Aug. 31, 2019) | F103: =SUM(C103:E103) -> 0
A104: B17 | B104: F - Of the initial 2014 cohort, how many completed the program in more than five years but in six years or less (after Aug. 31, 2018 and by Aug. 31, 2021) | F104: =SUM(C104:E104) -> 0
A105: B18 | B105: G - Total graduating within six years (sum of lines D, E, and F) | F105: =SUM(C105:E105) -> 0
A106: B19 | B106: H - Six-year graduation rate for 2014 cohort (G divided by C) | C106: =C105/C101 -> #DIV/0! | D106: =D105/D101 -> #DIV/0! | E106: =E105/E101 -> #DIV/0! | F106: =F105/F101 -> #DIV/0!

Sheet C.First-time Freshmen Admission
A1: C. FIRST-TIME, FIRST-YEAR (FRESHMAN) ADMISSION
B2: Applications
A3: C1 | B3: First-time, first-year, (freshmen) students: Provide the number of degree-seeking, first-time, first-year students who applied, were admitted, and enrolled (full- or part-time) in Fall 2022.
B6: • Include early decision, early action, and students who began studies during summer in this cohort.
B7: • Applicants should include only those students who fulfilled the requirements for consideration for admission (i.e., who completed actionable applications) and who have been notified of one of the following actions: admission, non-admission, placement on waiting list, or application withdrawn (by applicant or institution).
B8: • Admitted applicants should include wait-listed students who were subsequently offered admission.
B9: Total first-time, first-year (freshman) men who applied | E9: 8064 | J9: APPLIED | K9: ADMITTED | L9: ENROLLED
B10: Total first-time, first-year (freshman) women who applied | E10: 10766 | J10: =SUM(E9:E10) -> 18830 | K10: =SUM(E12:E13) -> 14158 | L10: MEN | M10: WOMEN | N10: TOT ENROLLED
L11: =SUM(E15:E16) -> 1618 | M11: =SUM(E18:E19) -> 1749 | N11: =SUM(L11:M11) -> 3367
B12: Total first-time, first-year (freshman) men who were admitted | E12: 6136
B13: Total first-time, first-year (freshman) women who were admitted | E13: 8022
B15: Total full-time, first-time, first-year (freshman) men who enrolled | E15: 1612
B16: Total part-time, first-time, first-year (freshman) men who enrolled | E16: 6
B18: Total full-time, first-time, first-year (freshman) women who enrolled | E18: 1741
B19: Total part-time, first-time, first-year (freshman) women who enrolled | E19: 8
A21: C2 | B21: Freshman wait-listed students
B22: Students who met admission requirements but whose final admission was contingent on space availability
E23: Yes | F23: No
B24: Do you have a policy of placing students on a waiting list? | F24: X
B25: If yes, please answer the questions below for Fall 2022 admissions:
B27: WAITING LIST | E27: TOTAL
B28: Number of qualified applicants offered a place on waiting list
B29: Number accepting a place on the waiting list
B30: Number of wait-listed students admitted
E31: Yes | F31: No
B32: Is your waiting list ranked? | F32: X
B33: If yes, do you release that information to students?
B34: Do you release that information to school counselors?
B36: Admission Requirements
A37: C3 | B37: High school completion requirement
B38: Check the appropriate box to identify your high school completion requirement for degree-seeking entering students:
A39: X | B39: High school diploma is required and GED is accepted
B40: High school diploma is required and GED is not accepted
B41: High school diploma or equivalent is not required
A43: C4 | B43: Does your institution require or recommend a general college-preparatory program for degree-seeking students?
A44: X | B44: Require
B45: Recommend
B46: Neither require nor recommend
A48: C5 | B48: Distribution of high school units required and/or recommended. Specify the distribution of academic high school course units required and/or recommended of all or most degree-seeking students using Carnegie units (one unit equals one year of study or its equivalent). If you use a different system for calculating units, please convert.
D49: Required | E49: Recommended
B50: English | D50: 4 | E50: 4
B51: Mathematics | D51: 4 | E51: 4
B52: Science | D52: 3 | E52: 4
B53: Social studies | D53: 3.5 | E53: 4
B54: Academic electives | D54: 2 | E54: 2
B55: Computer Science | D55: 1 | E55: 1
B56: Visual/Performing Arts | D56: 1 | E56: 1
B58: Total academic units: | D58: =SUM(D50:D56) -> 18.5 | E58: =SUM(E50:E56) -> 20
B60: Basis for Selection
A61: C6 | B61: Do you have an open admission policy, under which virtually all secondary school graduates or students with GED equivalency diplomas are admitted without regard to academic record, test scores, or other qualifications? If so, check which applies:
B62: Open admission policy as described above for all students
B63: Open admission policy as described above for most students, but--
B64: selective admission for out-of-state students
B65: selective admission to some programs
B66: other (explain):
A69: C7 | B69: Relative importance of each of the following academic and nonacademic factors in first-time, first-year, degree-seeking (freshman) admission decisions.
C70: Very Important | D70: Important | E70: Considered | F70: Not Considered
B71: Academic
B72: Rigor of secondary school record | E72: X
B73: Class rank | D73: X
B74: Academic GPA | C74: X
B75: Standardized test scores | E75: X
B76: Application Essay | F76: X
B77: Recommendation(s) | F77: X
B78: Nonacademic
B79: Interview | F79: X
B80: Extracurricular activities | F80: X
B81: Talent/ability | F81: X
B82: Character/personal qualities | F82: X
B83: First generation | F83: X
B84: Alumni/ae relation | F84: X
B85: Geographical residence | F85: X
B86: State residency | E86: X
B87: Religious affiliation/commitment | F87: X
B88: Racial/ethnic status | F88: X
B89: Volunteer work | F89: X
B90: Work experience | F90: X
B91: Level of applicant’s interest | F91: X
B93: SAT and ACT Policies
A94: C8 | B94: Entrance exams
F95: Yes | G95: No
B96: Does your institution make use of SAT, ACT, or SAT Subject Test scores in admission decisions for first-time, first-year, degree-seeking applicants? | F96: X
A97: C8A | B97: If yes, place check marks in the appropriate boxes below to reflect your institution’s policies for use in admission for Fall 2022.
C98: ADMISSION
C99: Require | D99: Recommend | E99: Require for Some | F99: Consider if Submitted | G99: Not Used
B100: SAT or ACT | F100: X
B101: ACT only
B102: SAT only
B103: SAT and SAT Subject Tests or ACT
B104: SAT Subject Tests only
A106: C8B | B106: If your institution will make use of the ACT in admission decisions for first-time, first-year, degree-seeking applicants for Fall 2022, please indicate which ONE of the following applies: (regardless of whether the writing score will be used in the admissions process):
B107: ACT with writing required
B108: ACT with writing recommended
A109: X | B109: ACT with or without writing accepted
A111: C8B | B111: If your institution will make use of the SAT in admission decisions for first-time, first-year, degree-seeking applicants
B112: for Fall 2022 please indicate which ONE of the following applies (regardless of whether the Essay score will be used
B113: in the admissions process:
B114: SAT with Essay component required
B115: SAT with Essay component recommended
A116: X | B116: SAT with or without Essay component accepted
...

Sheet D. Transfer Admission
A1: D. TRANSFER ADMISSION
B3: Fall Applicants
A4: D1 | F4: Yes | G4: No
B5: Does your institution enroll transfer students? | F5: X
B6: May transfer students earn advanced standing credit by transferring credits earned from course work completed at other colleges/universities? | F6: X
A8: D2 | B8: Provide the number of students who applied, were admitted, and enrolled as degree-seeking transfer students in Fall 2022.
D9: Applicants | E9: Admitted Applicants | F9: Enrolled Applicants
C10: Men | D10: 1722 | E10: 1311 | F10: 898
C11: Women | D11: 2180 | E11: 1454 | F11: 931
C12: Total | D12: =SUM(D10:D11) -> 3902 | E12: =SUM(E10:E11) -> 2765 | F12: =SUM(F10:F11) -> 1829
B14: Application for Admission
A15: D3 | B15: Indicate terms for which transfers may enroll:
A16: X | B16: Fall
B17: Winter
A18: X | B18: Spring
A19: X | B19: Summer
A21: D4 | F21: Yes | G21: No
B22: Must a transfer applicant have a minimum number of credits completed or else must apply as an entering freshman? | G22: X
A24: D5 | B24: Indicate all items required of transfer students to apply for admission:
C25: Required of All | D25: Recommended of All | E25: Recommended of Some | F25: Required of Some | G25: Not Required
B26: High school transcript | F26: X
B27: College transcript(s) | C27: X
B28: Essay or personal statement | G28: X
B29: Interview | G29: X
B30: Standardized test scores | F30: X
B31: Statement of good standing from prior institution(s) | C31: X
A33: D6 | B33: If a minimum high school grade point average is required of transfer applicants, specify (on a 4.0 scale):
A35: D7 | B35: If a minimum college grade point average is required of transfer applicants, specify (on a 4.0 scale): 2.00
A37: D8 | B37: List any other application requirements specific to transfer applicants: | E37: $40 Application Fee
A40: D9 | B40: List application priority, closing, notification, and candidate reply dates for transfer students. If applications are reviewed on a continuous or rolling basis, place a check mark in the “Rolling admission” column.
C41: Priority Date | D41: Closing Date | E41: Notification Date | F41: Reply Date | G41: Rolling Admission
B42: Fall | G42: X
B43: Winter
B44: Spring | G44: X
B45: Summer | G45: X
F47: Yes | G47: No
A48: D10 | B48: Does an open admission policy, if reported, apply to transfer students? | G48: X
A50: D11 | B50: Describe additional requirements for transfer admission, if applicable:
B53: Transfer Credit Policies | G53: Grade
A54: D12 | B54: Report the lowest grade earned for any course that may be transferred for credit: | G54: C *
F56: Number | G56: Unit Type
A57: D13 | B57: Maximum number of credits or courses that may be transferred from a two-year institution: | F57: 62 ** | G57: Credits
F59: Number | G59: Unit Type
A60: D14 | B60: Maximum number of credits or courses that may be transferred from a four-year institution: | F60: 93 ** | G60: Credits
G62: Number
A63: D16 | B63: Minimum number of credits that transfers must complete at your institution to earn a bachelor’s degree: | G63: 31
A65: D17 | B65: Describe other transfer credit policies: ( * ) Colleges and schools may allow the transfer of credits with a grade of D at their discretion [MSU AOP 12.12]. ( ** ) For curricula requiring 124 total credit hours. The last half of total hours applied toward graduation must be earned in a senior college, and at least the last 25% of semester credit hours of course work taken to fulfill degree requirements must be completed at Mississippi State University [MSU AOP 12.11].
B68: Military Service Transfer Credit Policies
A70: DANTES Subject Standardized Tests (DSST) Yes No
A71: D18 | B71: Does your institution accept the following military/veteran transfer credits:
F73: Yes | G73: No
B74: American Council on Education (ACE) | F74: X
B75: College Level Examination Program (CLEP) | F75: X
B76: DANTES Subject Standardized Tests (DSST) | G76: X
A78: D19 | F78: Number | G78: Unit Type
B79: Maximum number of credits or courses that may be transferred based on military education evaluated by the American Council on Education (ACE): | F79: 31 | G79: credit hours
A82: D20 | F82: Number | G82: Unit Type
B83: Maximum number of credits or courses that may be transferred based on Department of Defense supported prior learning assessments (College Level Examination Program (CLEP) or DANTES Subject Standardized Tests (DSST)): | F83: 31 | G83: credit hours
F87: Yes | G87: No
A88: D21 | B88: Are the military/veteran credit transfer policies on your website? | F88: X
A90: D22 | B90: Describe other military/veteran transfer credit policies unique to your institution:

Sheet E. Academic Offerings_Policies
A1: E. ACADEMIC OFFERINGS AND POLICIES
A2: E1 | B2: Special study options: Identify those programs available at your institution. Refer to the glossary for definitions.
A3: X | B3: Accelerated program
A4: X | B4: Cooperative education program
A5: X | B5: Cross-registration
A6: X | B6: Distance learning
A7: X | B7: Double major
A8: X | B8: Dual enrollment
A9: X | B9: English as a Second Language (ESL)
A10: X | B10: Exchange student program (domestic)
B11: External degree program
A12: X | B12: Honors Program
A13: X | B13: Independent study
A14: X | B14: Internships
A15: X | B15: Liberal arts/career combination
A16: X | B16: Student-designed major
A17: X | B17: Study abroad
A18: X | B18: Teacher certification program
B19: Weekend college
B20: Other (specify):
A23: E3 | B23: Areas in which all or most students are required to complete some course work prior to graduation:
A24: X | B24: Arts/fine arts
A25: X | B25: Computer literacy
A26: X | B26: English (including composition)
B27: Foreign languages
A28: X | B28: History
A29: X | B29: Humanities
A30: X | B30: Mathematics
A31: X | B31: Philosophy
A32: X | B32: Sciences (biological or physical)
A33: X | B33: Social science
B34: Other (describe):

Sheet F. Student Life
A1: F. STUDENT LIFE
A3: F1 | B3: Percentages of first-time, first-year (freshman) degree-seeking students and degree-seeking undergraduates enrolled in Fall 2022 who fit the following categories:
F4: First-time Freshmen | G4: Total Undergraduates
B5: Percent who are from out of state (exclude international/nonresident aliens) | F5: =1360/(SUM('B. Enrollment and Persistence'!J9)) -> 0.4039204 | G5: =5688/(SUM('B. Enrollment and Persistence'!J14)) -> 0.31073477
B6: Percent of men who are members of fraternities | F6: =400 / SUM('C.First-time Freshmen Admission'!E15:E16) -> 0.24721879 | G6: =1804/ 'B. Enrollment and Persistence'!H14 -> 0.19898522
B7: Percent of women who are members of sororities | F7: =647 / SUM('C.First-time Freshmen Admission'!E18:E19) -> 0.36992567 | G7: =2386 /'B. Enrollment and Persistence'!I14 -> 0.25825306
B8: Percent who live in college-owned, -operated, or -affiliated housing | F8: =3250/SUM('C.First-time Freshmen Admission'!E15:E19) -> 0.96525097 | G8: =5826/SUM('B. Enrollment and Persistence'!C14:F14) -> 0.3182737
B9: Percent who live off campus or commute | F9: =1-F8 -> 0.034749035 | G9: =1-G8 -> 0.6817263
B10: Percent of students age 25 and older | F10: 0.0021 | G10: 0.0837
B11: Average age of full-time students | F11: 18 | G11: 21
B12: Average age of all students (full- and part-time) | F12: 18 | G12: 21
A14: F2 | B14: Activities offered Identify those programs available at your institution.
A15: X | B15: Campus Ministries
A16: X | B16: Choral groups
A17: X | B17: Concert band
A18: X | B18: Dance
A19: X | B19: Drama/theater
A20: X | B20: International Student Organization
A21: X | B21: Jazz band
A22: X | B22: Literary magazine
A23: X | B23: Marching band
A24: X | B24: Model UN
A25: X | B25: Music ensembles
A26: X | B26: Musical theater
B27: Opera
A28: X | B28: Pep band
A29: X | B29: Radio station
A30: X | B30: Student government
A31: X | B31: Student newspaper
A32: X | B32: Student-run film society
A33: X | B33: Symphony orchestra
A34: X | B34: Television station
B35: Yearbook
A37: F3 | B37: ROTC (program offered in cooperation with Reserve Officers' Training Corps)
E39: On Campus | F39: At Cooperating Institution | G39: Name of Cooperating Institution
B40: Army ROTC is offered: | E40: X
B41: Naval ROTC is offered:
B42: Air Force ROTC is offered: | E42: X
A44: F4 | B44: Housing: Check all types of college-owned, -operated, or -affiliated housing available for undergraduates at your institution.
A45: X | B45: Coed dorms
A46: X | B46: Men's dorms
A47: X | B47: Women's dorms
B48: Apartments for married students
A49: X | B49: Apartments for single students
B50: Special housing for disabled students
B51: Special housing for international students
A52: X | B52: Fraternity/sorority housing
B53: Cooperative housing
A54: X | B54: Theme housing
B55: Wellness housing
A56: X | B56: Other housing options (specify): | C56: Co-Residential Housing

Sheet G. Annual Expenses
A1: G. ANNUAL EXPENSES
A3: G0 | B3: Please provide the URL of your institution’s net price calculator:
B4: https://npc.collegeboard.org/app/msu
B5: Provide 2022-23 academic year costs of attendance for the following categories that are applicable to your institution.
A7: X | B7: Check here if your institution's 2023-24 academic year costs of attendance are not available at this time and provide an approximate date (i.e., month/day) when your institution's final 2023-24 academic year costs of attendance will be available:
B8: 45108
A10: G1 | B10: Undergraduate full-time tuition, required fees, room and board List the typical tuition, required fees, and room and board for a full-time undergraduate student for the FULL 2021-22 academic year (30 semester or 45 quarter hours for institutions that derive annual tuition by multiplying credit hour cost by number of credits).
B12: • A full academic year refers to the period of time generally extending from September to June; usually equated to two semesters, two trimesters, three quarters, or the period covered by a four-one-four plan.
B13: • Room and board is defined as double occupancy and 19 meals per week or the maximum meal plan.
B14: • Required fees include only charges that all full-time students must pay that are not included in tuition (e.g., registration, health, or activity fees.)
B15: • Do not include optional fees (e.g., parking, laboratory use).
B17: PUBLIC INSTITUTIONS | D17: First-Year | E17: Undergraduates
C18: ^Tuition: In-state: | D18: 9248 | E18: 9248
C19: Tuition: Out-of-state: | D19: 25294 | E19: 25294
C20: Tuition: Non-resident alien | D20: 25294 | E20: 25294
B21: FOR ALL INSTITUTIONS
C22: Required Fees | D22: 150 | E22: 150
C23: Room and Board (on-campus): | D23: =SUM(D24:D25) -> 11190 | E23: =SUM(E24:E25) -> 11190
C24: *Room Only (on-campus): | D24: 6822 | E24: 6822
C25: **Board Only (on-campus meal plan): | D25: 4368 | E25: 4368
B27: ^Source: http://www.mississippi.edu/finance/downloads/fy2023_tuition.pdf
B28: *Source: http://www.mississippi.edu/finance/downloads/fy_2021-23_housing.pdf
B29: **Source: http://www.mississippi.edu/finance/downloads/fy_2021-23_meal.pdf
D31: Minimum | E31: Maximum
A32: G2 | B32: Number of credits per term a student can take for the stated full-time tuition | D32: 12
D34: Yes | E34: No
A35: G3 | B35: Do tuition and fees vary by year of study (e.g., sophomore, junior, senior)? | E35: X
D37: Yes | E37: No
A38: G4 | B38: Do tuition and fees vary by undergraduate instructional program? | E38: X
A40: G5 | B40: Provide the estimated expenses for a typical full-time undergraduate student:
C41: Residents | D41: Commuters (living at home) | E41: Commuters (not living at home)
B42: Books and supplies | C42: 1200 | D42: 1200 | E42: 1200
B43: Room only | E43: 6822
B44: Board only | D44: 4368 | E44: 4368
B45: Transportation | C45: 2335 | D45: 2567 | E45: 2335
B46: Other expenses | C46: 3210 | D46: 3210 | E46: 3210
A49: G6 | B49: Undergraduate per-credit-hour charges (tuition only)
B50: ^Tuition: In-state: | C50: 385.5
B51: Tuition: Out-of-state: | C51: 1054.25
B52: Tuition: Non-resident alien | C52: 1054.25

Sheet H. Financial Aid
A1: H. FINANCIAL AID
B3: Aid Awarded to Enrolled Undergraduates
A4: H1 | B4: Enter total dollar amounts awarded to enrolled full-time and less than full-time degree-seeking undergraduates (using the same cohort reported in CDS Question B1, “total degree-seeking” undergraduates) in the following categories.
B5: • If the data being reported are final figures for the 2021-2022 academic year (see the next item below), use the 2021-2022 academic year's CDS Question B1 cohort.
B6: • Include aid awarded to international students (i.e., those not qualifying for federal aid).
B7: • Aid that is non-need-based but that was used to meet need should be reported in the need-based aid column.
B8: • Do NOT include any aid related to the CARES Act or unique to the COVID-19 pandemic.
E10: 2022-2023 estimated | F10: 2021-2022 final
B11: Indicate the academic year for which data are reported for items H1, H2, H2A, and H6 below: | F11: X
B12: Which needs-analysis methodology does your institution use in awarding institutional aid? (Formerly H3)
A14: X | B14: Federal methodology (FM)
B15: Institutional methodology (IM)
B16: Both FM and IM
E18: Need-based $ (Include non-need-based aid used to meet need.) | F18: Non-need-based $ (Exclude non-need-based aid used to meet need.)
B19: Scholarships/Grants
B20: Federal | E20: 43772200
B21: State all states, not only the state in which your institution is located | E21: 10269287 | F21: 2130266
B22: Institutional: Endowed scholarships, annual gifts and tuition funded grants, awarded by the college, excluding athletic aid and tuition waivers (which are reported below). | E22: 39768835 | F22: 27607668
B23: Scholarships/grants from external sources (e.g. Kiwanis, National Merit) not awarded by the college | E23: 9139580 | F23: 3594131
B24: Total Scholarships/Grants | E24: =SUM(E20:E23) -> 102949902 | F24: =SUM(F20:F23) -> 33332065
B25: Self-Help
B26: Student loans from all sources (excluding parent loans) | E26: 84163022 | F26: 17931696
B27: Federal Work-Study | E27: 1530926
B28: State and other (e.g., institutional) work-study/employment (Note: Excludes Federal Work-Study captured above.)
B29: Total Self-Help | E29: =SUM(E26:E28) -> 85693948 | F29: =SUM(F26,F28) -> 17931696
B30: Other
B31: Parent Loans | E31: 13260354 | F31: 7170950
B32: Tuition Waivers Note: Reporting is optional. Report tuition waivers in this row if you choose to report them. Do not report tuition waivers elsewhere. | F32: 81944798
B33: Athletic Awards | F33: 10275804
A35: H2 | B35: Number of Enrolled Students Awarded Aid: List the number of degree-seeking full-time and less-than-full-time undergraduates who applied for and were awarded financial aid from any source.
B36: • Aid that is non-need-based but that was used to meet need should be counted as need- based aid.
B37: • Numbers should reflect the cohort awarded the dollars reported in H1.
B38: • In the chart below, students may be counted in more than one row, and full-time freshmen should also be counted as full-time undergraduates.
B39: • Do NOT include any aid related to the CARES Act or unique to the COVID-19 pandemic.
D41: First-time Full-time Freshmen | E41: Full-time Undergraduate (Incl. Fresh.) | F41: Less Than Full-time Undergraduate
B42: A | C42: Number of degree-seeking undergraduate students (CDS Item B1 if reporting on Fall 2021 cohort) | D42: 3388 | E42: 16794 | F42: 1790
B43: B | C43: Number of students in line a who applied for need-based financial aid | D43: 3038 | E43: 13231 | F43: 990
B44: C | C44: Number of students in line b who were determined to have financial need | D44: 2441 | E44: 11234 | F44: 863
B45: D | C45: Number of students in line c who were awarded any financial aid | D45: 2429 | E45: 11129 | F45: 812
B46: E | C46: Number of students in line d who were awarded any need-based scholarship or grant aid | D46: 2390 | E46: 10702 | F46: 661
B47: F | C47: Number of students in line d who were awarded any need-based self-help aid | D47: 1266 | E47: 6322 | F47: 473
B48: G | C48: Number of students in line d who were awarded any non-need-based scholarship or grant aid | D48: 454 | E48: 1244 | F48: 24
B49: H | C49: Number of students in line d whose need was fully met (exclude PLUS loans, unsubsidized loans, and private alternative loans) | D49: 486 | E49: 2046 | F49: 62
B50: I | C50: On average, the percentage of need that was met of students who were awarded any need-based aid. Exclude any aid that was awarded in excess of need as well as any resources that were awarded to replace EFC (PLUS loans, unsubsidized loans, and private alternative loans) | D50: 0.58 | E50: 0.55503476 | F50: 0.36773944
B51: J | C51: The average financial aid package of those in line d. Exclude any resources that were awarded to replace EFC (PLUS loans, unsubsidized loans, and private alternative loans) | D51: 16895.067 | E51: 15500.631 | F51: 8428.0197
B52: K | C52: Average need-based scholarship and grant award of those in line e | D52: 9651.8749 | E52: 8650.9782 | F52: 3948.1225
B53: L | C53: Average need-based self-help award (excluding PLUS loans, unsubsidized loans, and private alternative loans) of those in line f | D53: 2828.1556 | E53: 3726.7298 | F53: 3338.7505
B54: M | C54: Average need-based loan (excluding PLUS loans, unsubsidized loans, and private alternative loans) of those in line f who were awarded a need-based loan | D54: 3237.8116 | E54: 3487.2059 | F54: 3303.537
A56: H2A | B56: Number of Enrolled Students Awarded Non-need-based Scholarships and Grants: List the number of degree-seeking full-time and less-than-full-time undergraduates who had no financial need and who were awarded institutional non-need-based scholarship or grant aid.
B57: • Numbers should reflect the cohort awarded the dollars reported in H1.
B58: • In the chart below, students may be counted in more than one row, and full-time freshmen should also be counted as full-time undergraduates.
B59: • Do NOT include any aid related to the CARES Act or unique to the COVID-19 pandemic.
D60: First-time Full-time Freshmen | E60: Full-time Undergrad (Incl. Fresh.) | F60: Less Than Full-time Undergrad
B61: N | C61: Number of students in line a who had no financial need and who were awarded institutional non-need-based scholarship or grant aid (exclude those who were awarded athletic awards and tuition benefits) | D61: 585 | E61: 2517 | F61: 77
B62: O | C62: Average dollar amount of institutional non-need-based scholarship and grant aid awarded to students in line n | D62: 6266.2684 | E62: 5736.9333 | F62: 3217.5195
B63: P | C63: Number of students in line a who were awarded an institutional non-need-based athletic scholarship or grant | D63: 79 | E63: 403 | F63: 4
B64: Q | C64: Average dollar amount of institutional non-need-based athletic scholarships and grants awarded to students in line p | D64: 24931 | E64: 21600.067 | F64: 10748
C66: Note: These are the graduates and loan types to include and exclude in order to fill out CDS H4 and H5.
C67: Include:
C68: • 2020 undergraduate class: all students who started at your institution as first-time students and received a bachelor's degree between July 1, 2019 and June 30, 2020.
C69: • Only loans made to students who borrowed while enrolled at your institution.
C70: • Co-signed loans.
C71: Exclude
C72: • Students who transferred in.
C73: • Money borrowed at other institutions.
C74: • Parent loans
C75: • Students who did not graduate or who graduated with another degree or certificate (but no bachelor’s degree).
C76: • Any aid related to the CARE Act or unique the COVID-19 pandemic.
A78: H4 | B78: Provide the number of students in the 2022 undergraduate class who started at your institution as first-time students and received a bachelor's degree between July 1, 2021 and June 30, 2022. Exclude students who transferred into your institution. | F78: 2303
A79: H5 | B79: Number and percent of students in class (defined in H4 above) borrowing from federal, non-federal, and any loan sources, and the average (or mean) amount borrowed.
B80: • The “Average per-undergraduate-borrower cumulative principal borrowed,” is designed to provide better information about student borrowing from federal and nonfederal (institutional, state, commercial) sources.
B81: • The numbers, percentages, and averages for each row should be based only on the loan source specified for the particular row. For example, the federal loans average (row b) should only be the cumulative average of federal loans and the private loans average (row e) should only be the cumulative average of private loans.
C82: Source/Type of Loan | D82: Number in the class (defined in H4 above) who borrowed from the types of loans specified in the first column | E82: Percent of the class (defined above) who borrowed from the types of loans specified in the first column (nearest 1%) | F82: Average per-undergraduate-borrower cumulative principal borrowed from the types of loans specified in the first column (nearest $1)
B84: A | C84: Any loan program: Federal Perkins, Federal Stafford Subsidized and Unsubsidized, institutional, state, private loans that your institution is aware of, etc. Include both Federal Direct Student Loans and Federal Family Education Loans. | D84: 1205 | E84: 0.5232 | F84: 25796.587
B85: B | C85: Federal loan programs: Federal Perkins, Federal Stafford Subsidized and Unsubsidized. Include both Federal Direct Student Loans and Federal Family Education Loans. | D85: 1160 | E85: 0.5037 | F85: 19974.063
B86: C | C86: Institutional loan programs. | D86: 51 | E86: 0.0221 | F86: 23588.471
B87: D | C87: State loan programs.
B88: E | C88: Private student loans made by a bank or lender. | D88: 200 | E88: 0.0868 | F88: 33559.81
B90: Aid to Undergraduate Degree-seeking Nonresident Aliens
B91: • Report numbers and dollar amounts for the same academic year checked in item H1
A93: H6 | B93: Indicate your institution’s policy regarding institutional scholarship and grant aid for undergraduate degree-seeking nonresident aliens:
B94: Institutional need-based scholarship or grant aid is available
A95: X | B95: Institutional non-need-based scholarship or grant aid is available
B96: Institutional scholarship or grant aid is not available
B98: If institutional financial aid is available for undergraduate degree-seeking nonresident aliens, provide the number of undergraduate degree-seeking nonresident aliens who were awarded need-based or non-need-based aid: | F98: 283
B100: Average dollar amount of institutional financial aid awarded to undergraduate degree-seeking nonresident aliens: | F100: 2571.45
B102: Total dollar amount of institutional financial aid awarded to undergraduate degree-seeking nonresident aliens: | F102: 1432297
A104: H7 | B104: Check off all financial aid forms nonresident alien first-year financial aid applicants must submit:
B105: Institution’s own financial aid form
B106: CSS/Financial Aid PROFILE
B107: International Student’s Financial Aid Application
B108: International Student’s Certification of Finances
A109: X | B109: Other (specify):
B110: General Scholarship Application
B112: Process for First-Year/Freshman Students
A114: H8 | B114: Check off all financial aid forms domestic first-year (freshman) financial aid applicants must submit:
A116: X | B116: FAFSA
B117: Institution's own financial aid form
B118: CSS/Financial Aid PROFILE
A119: X | B119: State aid form
...

Sheet I. Instructional Faculty-Class
A1: I. INSTRUCTIONAL FACULTY AND CLASS SIZE
A3: I1 | B3: Please report the number of instructional faculty members in each category for Fall 2022. Include faculty who are on your institution’s payroll on the census date your institution uses for IPEDS/AAUP.
I5: Full-Time | J5: Part-Time | K5: Total
B6: A | C6: Total number of instructional faculty | I6: 1072 | J6: 368 | K6: =SUM(I6:J6) -> 1440 | M6: 1072 | N6: FT Fac | O6: 368 | P6: PT Fac
B7: B | C7: Total number who are members of minority groups | I7: 221 | J7: 82 | K7: =SUM(I7:J7) -> 303 | M7: =O7 -> 122.66667 | N7: 1/3 PT Fac | O7: =O6/3 -> 122.66667 | P7: 1/3 PT Fac
B8: C | C8: Total number who are women | I8: 468 | J8: 197 | K8: =SUM(I8:J8) -> 665 | M8: =SUM(M6:M7) -> 1194.6667
B9: D | C9: Total number who are men | I9: 604 | J9: 171 | K9: =SUM(I9:J9) -> 775
B10: E | C10: Total number who are nonresident aliens (international) | I10: 74 | J10: 4 | K10: =SUM(I10:J10) -> 78
B11: F | C11: Total number with doctorate, or other terminal degree | I11: 889 | J11: 158 | K11: =SUM(I11:J11) -> 1047
B12: G | C12: Total number whose highest degree is a master's but not a terminal master's | I12: 179 | J12: 180 | K12: =SUM(I12:J12) -> 359
B13: H | C13: Total number whose highest degree is a bachelor's | I13: 4 | J13: 18 | K13: =SUM(I13:J13) -> 22
B14: I | C14: Total number whose highest degree is unknown or other (Note: Items f, g, h, and i must sum up to item a.) | I14: 0 | J14: 12 | K14: =SUM(I14:J14) -> 12
B15: J | C15: Total number in stand-alone graduate/ professional programs in which faculty teach virtually only graduate-level students | I15: 0 | J15: 0 | K15: =SUM(I15:J15) -> 0
A17: I2 | B17: Student to Faculty Ratio
B18: Report the Fall 2022 ratio of full-time equivalent students (full-time plus 1/3 part time) to full-time equivalent instructional faculty (full time plus 1/3 part time).
B20: • Exclude both faculty and students in stand-alone graduate or professional programs such as medicine, law, veterinary, dentistry, social work, business, or public health in which faculty teach virtually only graduate-level students.
B21: • Do not count undergraduate or graduate student teaching assistants as faculty.
M22: 18343 | N22: FT Students
B23: Fall 2022 Student to Faculty ratio | G23: =J23/J24 -> 16.426339 | H23: to 1 | I23: (based on | J23: =M24 -> 19624 | K23: students | M23: 1281 | N23: 1/3 PT STUDENTS
I24: and | J24: =M8 -> 1194.6667 | K24: faculty). | M24: =SUM(M22:M23) -> 19624
B26: Instructional Faculty is defined as those members of the instructional-research staff whose major regular assignment is instruction, including those with released time for research. Use the chart below to determine inclusions and exclusions:
J27: Full-time | K27: Part-time
C28: (a) instructional faculty in preclinical and clinical medicine, faculty who are not paid (e.g., those who donate their services or are in the military), or research-only faculty, post-doctoral fellows, or pre-doctoral fellows | J28: Exclude | K28: Include only if they teach one or more non-clinical credit courses
C29: (b) administrative officers with titles such as dean of students, librarian, registrar, coach, and the like, even though they may devote part of their time to classroom instruction and may have faculty status | J29: Exclude | K29: Include if they teach one or more non-clinical credit courses
C30: (c) other administrators/staff who teach one or more non-clinical credit courses even though they do not have faculty status | J30: Exclude | K30: Include
C31: (d) undergraduate or graduate students who assist in the instruction of courses, but have titles such as teaching assistant, teaching fellow, and the like | J31: Exclude | K31: Exclude
C32: (e) faculty on sabbatical or leave with pay | J32: Include | K32: Exclude
C33: (f) faculty on leave without pay | J33: Exclude | K33: Exclude
C34: (g) replacement faculty for faculty on sabbatical leave or leave with pay | J34: Exclude | K34: Include
B36: Full-time instructional faculty: faculty employed on a full-time basis for instruction (including those with released time for research)
B37: Part-time instructional faculty: Adjuncts and other instructors being paid solely for part-time classroom instruction. Also includes full-time faculty teaching less than two semesters, three quarters, two trimesters, or two four-month sessions. Employees who are not considered full-time instructional faculty but who teach one or more non-clinical credit courses may be counted as part-time faculty.
B38: Minority faculty: includes faculty who designate themselves as Black, non-Hispanic; American Indian or Alaska Native; Asian, Native Hawaiian or other Pacific Islander, or Hispanic.
B39: Doctorate: includes such degrees as Doctor of Philosophy, Doctor of Education, Doctor of Juridical Science, and Doctor of Public Health in any field such as arts, sciences, education, engineering, business, and public administration. Also includes terminal degrees formerly designated as “first professional,” including dentistry (DDS or DMD), medicine (MD), optometry (OD), osteopathic medicine (DO), pharmacy (DPharm or BPharm), podiatric medicine (DPM), veterinary medicine (DVM), chiropractic (DC or DCM), or law (JD).
B40: Terminal degree: the highest degree in a field: example, M. Arch (architecture) and MFA (master of fine arts).
A42: I3 | B42: Undergraduate Class Size
B43: In the table below, please use the following definitions to report information about the size of classes and class sections offered in the Fall 2022 term.
B44: • Please include classes that have been moved online in response to the COVID-19 pandemic.
A45: I3 | B45: Number of Class Sections with Undergraduates Enrolled
A47: I3 | B47: Undergraduate Class Size (provide numbers)
A48: I3 | B48: CLASS SECTIONS | D48: 2-9 | E48: 10-19 | F48: 20-29 | G48: 30-39 | H48: 40-49 | I48: 50-99 | J48: 100+ | K48: Total
A49: I3 | D49: 482 | E49: 941 | F49: 743 | G49: 303 | H49: 201 | I49: 324 | J49: 117 | K49: =SUM(D49:J49) -> 3111
A51: I3 | B51: CLASS SUB-SECTIONS | D51: 2-9 | E51: 10-19 | F51: 20-29 | G51: 30-39 | H51: 40-49 | I51: 50-99 | J51: 100+ | K51: Total
A52: I3 | D52: 262 | E52: 215 | F52: 126 | G52: 97 | H52: 20 | I52: 14 | J52: 6 | K52: =SUM(D52:J52) -> 740
B54: Class Sections: A class section is an organized course offered for credit, identified by discipline and number, meeting at a stated time or times in a classroom or similar setting, and not a subsection such as a laboratory or discussion session. Undergraduate class sections are defined as any sections in which at least one degree-seeking undergraduate student is enrolled for credit. Exclude distance learning classes and noncredit classes and individual instruction such as dissertation or thesis research, music instruction, or one-to-one readings. Exclude students in independent study, co-operative programs, internships, foreign language taped tutor sessions, practicums, and all students in one-on-one classes. Each class section should be counted only once and should not be duplicated because of course catalog cross-listings.
B55: Class Subsections: A class subsection includes any subsection of a course, such as laboratory, recitation, and discussion subsections that are supplementary in nature and are scheduled to meet separately from the lecture portion of the course. Undergraduate subsections are defined as any subsections of courses in which degree-seeking undergraduate students enrolled for credit. As above, exclude noncredit classes and individual instruction such as dissertation or thesis research, music instruction, or one-to-one readings. Each class subsection should be counted only once and should not be duplicated because of cross-listings.
B56: Using the above definitions, please report for each of the following class-size intervals the number of class sections and class subsections offered in Fall 2022. For example, a lecture class with 800 students who met at another time in 40 separate labs with 20 students should be counted once in the “100+” column in the class section column and 40 times under the “20-29” column of the class subsections table.

Sheet J. Degrees Conferred
A1: J. DEGREES CONFERRED
A3: J1 | B3: Degrees conferred between July 1, 2021 and June 30, 2022
B4: For each of the following discipline areas, provide the percentage of diplomas/certificates, associate, and bachelor’s degrees awarded.
B5: • To determine the percentage, use majors, not headcount (e.g., students with one degree but a double major will be represented twice).
B6: • Calculate the percentage from your institution’s IPEDS Completions by using the sum of 1st and 2nd majors for each CIP code as the numerator and the sum of the Grand Total by 1st Majors and the Grand Total by 2nd major as the denominator. If you prefer, you can compute the percentages using 1st majors only.
B7: Category | C7: Diploma/Certificates | D7: Associate | E7: Bachelor’s | F7: CIP 2020 Categories to Include | G7: IPEDS 1st Major #
B8: Agriculture | E8: =G8/$G$46 -> 0.05744186 | F8: 01 | G8: 247
B9: Natural resources and conservation | E9: =G9/$G$46 -> 0.026976744 | F9: 03 | G9: 116
B10: Architecture | E10: =G10/$G$46 -> 0.012790698 | F10: 04 | G10: 55
B11: Area, ethnic, and gender studies | E11: =G11/$G$46 -> 0 | F11: 5
B12: Communication/journalism | E12: =G12/$G$46 -> 0.038372093 | F12: 09 | G12: 165
B13: Communication technologies | E13: =G13/$G$46 -> 0 | F13: 10
B14: Computer and information sciences | E14: =G14/$G$46 -> 0.019302326 | F14: 11 | G14: 83
B15: Personal and culinary services | E15: =G15/$G$46 -> 0.0011627907 | F15: 12 | G15: 5
B16: Education | E16: =G16/$G$46 -> 0.082093023 | F16: 13 | G16: 353
B17: Engineering | E17: =G17/$G$46 -> 0.16255814 | F17: 14 | G17: 699
B18: Engineering technologies | E18: =G18/$G$46 -> 0.017906977 | F18: 15 | G18: 77
B19: Foreign languages, literatures, and linguistics | E19: =G19/$G$46 -> 0.0076744186 | F19: 16 | G19: 33
B20: Family and consumer sciences | E20: =G20/$G$46 -> 0.018372093 | F20: 19 | G20: 79
B21: Law/legal studies | E21: =G21/$G$46 -> 0 | F21: 22
B22: English | E22: =G22/$G$46 -> 0.0053488372 | F22: 23 | G22: 23
B23: Liberal arts/general studies | E23: =G23/$G$46 -> 0.013488372 | F23: 24 | G23: 58
B24: Library science | E24: =G24/$G$46 -> 0 | F24: 25
B25: Biological/life sciences | E25: =G25/$G$46 -> 0.067674419 | F25: 26 | G25: 291
B26: Mathematics and statistics | E26: =G26/$G$46 -> 0.008372093 | F26: 27 | G26: 36
B27: Military science and military technologies | E27: =G27/$G$46 -> 0 | F27: 28 & 29
B28: Interdisciplinary studies | E28: =G28/$G$46 -> 0.053023256 | F28: 30 | G28: 228
B29: Parks and recreation | E29: =G29/$G$46 -> 0.059069767 | F29: 31 | G29: 254
B30: Philosophy and religious studies | E30: =G30/$G$46 -> 0.0013953488 | F30: 38 | G30: 6
B31: Theology and religious vocations | E31: =G31/$G$46 -> 0 | F31: 39
B32: Physical sciences | E32: =G32/$G$46 -> 0.026046512 | F32: 40 | G32: 112
B33: Science technologies | E33: =G33/$G$46 -> 0 | F33: 41
B34: Psychology | E34: =G34/$G$46 -> 0.061395349 | F34: 42 | G34: 264
B35: Homeland Security, law enforcement, firefighting, and protective services | E35: =G35/$G$46 -> 0 | F35: 43
B36: Public administration and social services | E36: =G36/$G$46 -> 0.0086046512 | F36: 44 | G36: 37
B37: Social sciences | E37: =G37/$G$46 -> 0.038139535 | F37: 45 | G37: 164
B38: Construction trades | E38: =G38/$G$46 -> 0 | F38: 46
B39: Mechanic and repair technologies | E39: =G39/$G$46 -> 0 | F39: 47
B40: Precision production | E40: =G40/$G$46 -> 0 | F40: 48
B41: Transportation and materials moving | E41: =G41/$G$46 -> 0 | F41: 49
B42: Visual and performing arts | E42: =G42/$G$46 -> 0.011860465 | F42: 50 | G42: 51
B43: Health professions and related programs | E43: =G43/$G$46 -> 0.0030232558 | F43: 51 | G43: 13
B44: Business/marketing | E44: =G44/$G$46 -> 0.19395349 | F44: 52 | G44: 834
B45: History | E45: =G45/$G$46 -> 0.0039534884 | F45: 54 | G45: 17
B46: TOTAL (should = 100%) | E46: =SUM(E8:E45) -> 1 | G46: =SUM(G8:G45) -> 4300
